mpython/__init__.py
mpython/_version.py
mpython/array.py
mpython/cell.py
mpython/exceptions.py
mpython/matlab_class.py
mpython/matlab_function.py
mpython/runtime.py
mpython/sparse_array.py
mpython/struct.py
mpython/utils.py
mpython/core/__init__.py
mpython/core/base_types.py
mpython/core/delayed_types.py
mpython/core/mixin_types.py
mpython/core/wrapped_types.py
mpython/helpers/__init__.py
mpython/helpers/np.py
mpython_core-25.4a3.dist-info/licenses/LICENSE
mpython_core-25.4a3.dist-info/METADATA
mpython_core-25.4a3.dist-info/WHEEL
mpython_core-25.4a3.dist-info/top_level.txt
mpython_core-25.4a3.dist-info/RECORD
