Metadata-Version: 2.4
Name: mpython-core
Version: 25.4a3
Summary: Core Python elements for wrapped MPython packages.
Author-email: Johan Medrano <johan.medrano@ucl.ac.uk>, Yael Balbastre <y.balbastre@ucl.ac.uk>
License:                     GNU GENERAL PUBLIC LICENSE
Project-URL: Repository, https://github.com/MPython-Package-Factory/mpython-core
Classifier: Development Status :: 3 - Alpha
Classifier: License :: OSI Approved :: GNU General Public License v2 (GPLv2)
Classifier: Programming Language :: Python :: 3.3
Classifier: Programming Language :: Python :: 3.4
Classifier: Programming Language :: Python :: 3.5
Classifier: Programming Language :: Python :: 3.6
Classifier: Programming Language :: Python :: 3.7
Classifier: Programming Language :: Python :: 3.8
Classifier: Programming Language :: Python :: 3.9
Classifier: Programming Language :: Python :: 3.10
Classifier: Programming Language :: Python :: 3.11
Classifier: Programming Language :: Python :: 3.12
Requires-Python: <3.14,>=3.3
License-File: LICENSE
Requires-Dist: numpy
Dynamic: license-file
